nonebot_plugin_herocard/__init__.py
nonebot_plugin_herocard-1.0.5.dist-info/WHEEL
nonebot_plugin_herocard-1.0.5.dist-info/METADATA
nonebot_plugin_herocard-1.0.5.dist-info/RECORD
