Metadata-Version: 2.1
Name: nonebot-plugin-herocard
Version: 1.0.5
Summary: 用于提取本子🥵标题关键词的 NoneBot2 插件
License: MIT
Author-email: Xie-Tiao <1183004468@qq.com>
Requires-Python: >=3.8
Requires-Dist: nonebot-adapter-onebot>=2.0.0b1
Requires-Dist: nonebot2>=2.0.0b2
Project-URL: Homepage, https://github.com/Xie-Tiao/nonebot_plugin_herocard
Project-URL: Repository, https://github.com/Xie-Tiao/nonebot_plugin_herocard
